rstms_cloudflare/__init__.py
rstms_cloudflare/cli.py
rstms_cloudflare/cloudflare.py
rstms_cloudflare/exception_handler.py
rstms_cloudflare/import_records.py
rstms_cloudflare/shell.py
rstms_cloudflare/version.py
rstms_cloudflare-1.2.10.dist-info/entry_points.txt
rstms_cloudflare-1.2.10.dist-info/licenses/LICENSE
rstms_cloudflare-1.2.10.dist-info/WHEEL
rstms_cloudflare-1.2.10.dist-info/METADATA
rstms_cloudflare-1.2.10.dist-info/RECORD
